odoo/addons/product_category_active/README.rst
odoo/addons/product_category_active/__init__.py
odoo/addons/product_category_active/__manifest__.py
odoo/addons/product_category_active/i18n/ca.po
odoo/addons/product_category_active/i18n/es.po
odoo/addons/product_category_active/i18n/hr.po
odoo/addons/product_category_active/i18n/hr_HR.po
odoo/addons/product_category_active/i18n/it.po
odoo/addons/product_category_active/i18n/product_category_active.pot
odoo/addons/product_category_active/i18n/pt.po
odoo/addons/product_category_active/migrations/16.0.2.0.0/post-migration.py
odoo/addons/product_category_active/models/__init__.py
odoo/addons/product_category_active/models/product_category.py
odoo/addons/product_category_active/readme/CONTRIBUTORS.md
odoo/addons/product_category_active/readme/DESCRIPTION.md
odoo/addons/product_category_active/readme/USAGE.md
odoo/addons/product_category_active/static/description/icon.png
odoo/addons/product_category_active/static/description/index.html
odoo/addons/product_category_active/tests/__init__.py
odoo/addons/product_category_active/tests/test_product_category_active.py
odoo/addons/product_category_active/views/product_views.xml
odoo_addon_product_category_active-18.0.1.0.0.7.dist-info/METADATA
odoo_addon_product_category_active-18.0.1.0.0.7.dist-info/WHEEL
odoo_addon_product_category_active-18.0.1.0.0.7.dist-info/top_level.txt
odoo_addon_product_category_active-18.0.1.0.0.7.dist-info/RECORD
